ovh_dynhost/__init__.py
ovh_dynhost/__version__.py
ovh_dynhost/ovh_dynhost.py
ovh_dynhost-0.5.dist-info/LICENSE
ovh_dynhost-0.5.dist-info/METADATA
ovh_dynhost-0.5.dist-info/WHEEL
ovh_dynhost-0.5.dist-info/entry_points.txt
ovh_dynhost-0.5.dist-info/top_level.txt
ovh_dynhost-0.5.dist-info/RECORD
