Metadata-Version: 2.1
Name: ovh-dynhost
Version: 0.5
Summary: A script to update the OVH DynHost with your current public IP
Home-page: https://github.com/rubendibattista/ovh-dynhost
Author: Ruben Di Battista
Author-email: rubendibattista@gmail.com
License: BSD
Platform: UNKNOWN
Classifier: Development Status :: 5 - Production/Stable
Classifier: Environment :: Console
Classifier: Intended Audience :: System Administrators
Classifier: License :: OSI Approved :: BSD License
Classifier: Programming Language :: Python :: 3
Classifier: Topic :: Internet :: Name Service (DNS)
Requires-Python: >=3.5.0
Requires-Dist: requests
Requires-Dist: docopt
